orthographic_projector/__init__.py
orthographic_projector/orthographic_projector.cpython-312-x86_64-linux-gnu.so
orthographic_projector-0.2.1.dist-info/METADATA
orthographic_projector-0.2.1.dist-info/WHEEL
orthographic_projector-0.2.1.dist-info/RECORD
orthographic_projector-0.2.1.dist-info/licenses/LICENSE
