Metadata-Version: 2.4
Name: orthographic_projector
Version: 0.2.1
Requires-Dist: numpy>=1.26
Requires-Dist: opencv-python>=4.9
Requires-Dist: toml>=0.10.0
License-File: LICENSE
Summary: Generate orthographic projections from a Point Cloud.
Requires-Python: >=3.10
Project-URL: repository, https://github.com/akaTsunemori/orthographic_projector
